siften/__init__.py
siften/core.py
siften/common/__init__.py
siften/common/keys/__init__.py
siften/common/keys/api_keys.py
siften/common/services/__init__.py
siften/common/services/add_to_database.py
siften/common/services/base_strategy.py
siften/common/services/binance_api.py
siften/common/services/binance_order_executor.py
siften/common/services/database_handler.py
siften/common/services/exchange_api.py
siften/common/services/order_executor.py
siften/common/services/position_management_facade.py
siften/common/services/service_registry.py
siften/common/services/strategy_logic.py
siften/common/services/strategy_logic_facade.py
siften/common/services/technical_analysis_facade.py
siften/common/services/transaction_cost_model.py
siften/common/utils/__init__.py
siften/common/utils/event_handler.py
siften/common/utils/logging_handler.py
siften/common/utils/time_handler.py
siften/strategies/__init__.py
siften/strategies/lambda_function.py
siften/strategies/strategy_facade.py
siften/strategies/trend_following/__init__.py
siften/strategies/trend_following/trend_following.py
siften/strategies/trend_following/trend_following_logic.py
siften-0.1.0.dist-info/METADATA
siften-0.1.0.dist-info/WHEEL
siften-0.1.0.dist-info/RECORD
