Metadata-Version: 2.3
Name: siften
Version: 0.1.0
Summary: A Python library for Siften.
Project-URL: Homepage, https://github.com/siften-technologies/siften-core
Author-email: Nick Lamb <nick@siften.com>
Classifier: Development Status :: 3 - Alpha
Classifier: Intended Audience :: Developers
Classifier: License :: OSI Approved :: MIT License
Classifier: Operating System :: OS Independent
Classifier: Programming Language :: Python :: 3
Requires-Python: >=3.8
Requires-Dist: boto3
Requires-Dist: python-dotenv
Requires-Dist: requests
Provides-Extra: dev
Requires-Dist: black>=22.0; extra == 'dev'
Requires-Dist: pytest>=7.0; extra == 'dev'
